README.md
setup.py
pyenv_wsio/__init__.py
pyenv_wsio/_client.py
pyenv_wsio/_events.py
pyenv_wsio/_namespace.py
pyenv_wsio/_packet.py
pyenv_wsio/_wsio.py
pyenv_wsio.egg-info/PKG-INFO
pyenv_wsio.egg-info/SOURCES.txt
pyenv_wsio.egg-info/dependency_links.txt
pyenv_wsio.egg-info/requires.txt
pyenv_wsio.egg-info/top_level.txt