Metadata-Version: 2.1
Name: pyenv-wsio
Version: 0.0.4
Summary: VirtualPyEnv websocket library
Home-page: https://github.com/graphisoft-python/pyenv_wsio
Author: beanjs
Author-email: 502554248@qq.com
License: MIT Licence
Platform: UNKNOWN
Classifier: Operating System :: OS Independent
Classifier: Programming Language :: Python :: 2.7
Classifier: License :: OSI Approved :: MIT License
